{
 "lane": "l1",
 "n_rows": 50000,
 "connect_s": 0.789,
 "engine_version": "17.10 (Debian 17.10-1.pgdg13+1)",
 "schema_s": 0.022,
 "ingest_s": 0.68,
 "ingest_rows_per_s": 73784.3,
 "read_mean_ms": 0.5974,
 "read_p50_ms": 0.4582,
 "read_p95_ms": 1.2408,
 "read_p99_ms": 1.4085,
 "read_n": 3060,
 "insert_mean_ms": 2.3115,
 "insert_p50_ms": 2.1344,
 "insert_p95_ms": 3.8118,
 "insert_p99_ms": 4.356,
 "insert_n": 979,
 "update_mean_ms": 2.1874,
 "update_p50_ms": 2.0692,
 "update_p95_ms": 3.4481,
 "update_p99_ms": 3.9591,
 "update_n": 961,
 "oltp_ops_per_s": 807.4
}