{
 "lane": "l1",
 "n_rows": 20000000,
 "connect_s": 0.116,
 "engine_version": "17.10 (Debian 17.10-1.pgdg13+1)",
 "schema_s": 0.018,
 "ingest_s": 60.39,
 "ingest_rows_per_s": 331199.0,
 "read_mean_ms": 1.1766,
 "read_p50_ms": 1.0312,
 "read_p95_ms": 1.6808,
 "read_p99_ms": 1.8659,
 "read_n": 3068,
 "insert_mean_ms": 2.4769,
 "insert_p50_ms": 2.5141,
 "insert_p95_ms": 2.8359,
 "insert_p99_ms": 3.0415,
 "insert_n": 1006,
 "update_mean_ms": 3.9071,
 "update_p50_ms": 3.8396,
 "update_p95_ms": 4.5445,
 "update_p99_ms": 5.0221,
 "update_n": 926,
 "oltp_ops_per_s": 514.4
}